{"is_source_file": true, "format": "Python", "description": "This file defines a Flask API endpoint for fetching session statistics. It uses Flask's MethodView and Flask-Smorest for schema validation and response handling. The endpoint retrieves session statistics via a service layer and handles errors when data is unavailable.", "external_files": ["app.schemas", "app.services.session_service"], "external_methods": ["session_service.get_stats", "blp.abort"], "published": [], "classes": [{"name": "StatsAPI", "description": "A Flask MethodView class providing an API endpoint to fetch session statistics based on a session ID."}], "methods": [{"name": "get(self, query_args)", "description": "Handles GET requests to retrieve statistics for a session, validates input query parameters, interacts with the session service, and manages error responses.", "scope": "StatsAPI", "scopeKind": "class"}], "calls": ["session_service.get_stats", "blp.abort"], "search-terms": ["stats", "session_id", "Flask MethodView", "session_service", "stats API", "stats endpoint"], "state": 2, "file_id": 12, "knowledge_revision": 46, "git_revision": "a3fdfd1b3158a74932248849fb695afdb126a631", "revision_history": [{"27": ""}, {"46": "a3fdfd1b3158a74932248849fb695afdb126a631"}], "ctags": [{"_type": "tag", "name": "StatsAPI", "path": "/home/kavia/workspace/code-generation/execution-session-management-api-691-700/backend_api/app/routes/stats.py", "pattern": "/^class StatsAPI(MethodView):$/", "language": "Python", "kind": "class"}, {"_type": "tag", "name": "blp", "path": "/home/kavia/workspace/code-generation/execution-session-management-api-691-700/backend_api/app/routes/stats.py", "pattern": "/^blp = Blueprint($/", "language": "Python", "kind": "variable"}, {"_type": "tag", "name": "get", "path": "/home/kavia/workspace/code-generation/execution-session-management-api-691-700/backend_api/app/routes/stats.py", "pattern": "/^    def get(self, query_args):$/", "language": "Python", "kind": "member", "signature": "(self, query_args)", "scope": "StatsAPI", "scopeKind": "class"}], "hash": "8e5b0c146911a9dffcd4045b9895e191", "format-version": 4, "code-base-name": "backend_api", "filename": "backend_api/app/routes/stats.py", "fields": [{"name": "blp = Blueprint(", "scope": "", "scopeKind": "", "description": "unavailable"}]}